image_hashing/__init__.py
image_hashing/image_hashing.py
flare_image_hashing-0.0.6.dist-info/LICENSE
flare_image_hashing-0.0.6.dist-info/METADATA
flare_image_hashing-0.0.6.dist-info/WHEEL
flare_image_hashing-0.0.6.dist-info/top_level.txt
flare_image_hashing-0.0.6.dist-info/RECORD
