Metadata-Version: 2.1
Name: flare-image-hashing
Version: 0.0.6
Summary: A small example package
Home-page: https://github.com/Flare-FYDP/image-hashing
Author: flare
Author-email: author@example.com
License: UNKNOWN
Project-URL: Bug Tracker, https://github.com/Flare-FYDP/image-hashing/issues
Platform: UNKNOWN
Classifier: Programming Language :: Python :: 3
Classifier: License :: OSI Approved :: MIT License
Classifier: Operating System :: OS Independent
Requires-Python: >=3.6
License-File: LICENSE
Requires-Dist: imagehash
Requires-Dist: Pillow
